{
    "msg": 200,
    "data": [
        {
            "id": 1,
            "name": "【12.12提前购】【新品上市】A407UB-顽石14寸轻薄窄边框笔记本（Windows10home/i5-7200U/4G内存/500GB+128G SSD)-冰柱金",
            "price": 4599,
            "img": "static/images/list"
        },
        {
            "id": 2,
            "name": "【12.12提前购】灵耀S 2代 S4300UN-14英寸炫彩窄边框轻薄本（Windows10home/i5-8250U/8GB/512GB SSD/MX150显卡)-冰钻金",
            "price": 5499,
            "img": "static/images/list"
        },
        {
            "id": 3,
            "name": "【12.12提前购】【新品上市】A407UB-顽石14寸轻薄窄边框笔记本（Windows10home/i5-7200U/4G内存/500GB+128G SSD)-冰柱金",
            "price": 8599,
            "img": "static/images/list"
        },
        {
            "id": 4,
            "name": "【12.12提前购】【新品上市】A407UB-顽石14寸轻薄窄边框笔记本（Windows10home/i5-7200U/4G内存/500GB+128G SSD)-冰柱金",
            "price": 6599,
            "img": "static/images/list"
        },
        {
            "id": 5,
            "name": "【12.12提前购】【新品上市】A407UB-顽石14寸轻薄窄边框笔记本（Windows10home/i5-7200U/4G内存/500GB+128G SSD)-冰柱金",
            "price": 7599,
            "img": "static/images/list"
        },
        {
            "id": 6,
            "name": "【12.12提前购】【新品上市】A407UB-顽石14寸轻薄窄边框笔记本（Windows10home/i5-7200U/4G内存/500GB+128G SSD)-冰柱金",
            "price": 4599,
            "img": "static/images/list"
        },
        {
            "id": 7,
            "name": "【12.12提前购】灵耀S 2代 S4300UN-14英寸炫彩窄边框轻薄本（Windows10home/i5-8250U/8GB/512GB SSD/MX150显卡)-冰钻金",
            "price": 5499,
            "img": "static/images/list"
        },
        {
            "id": 8,
            "name": "【12.12提前购】【新品上市】A407UB-顽石14寸轻薄窄边框笔记本（Windows10home/i5-7200U/4G内存/500GB+128G SSD)-冰柱金",
            "price": 8599,
            "img": "static/images/list"
        },
        {
            "id":9,
            "name": "【12.12提前购】【新品上市】A407UB-顽石14寸轻薄窄边框笔记本（Windows10home/i5-7200U/4G内存/500GB+128G SSD)-冰柱金",
            "price": 6599,
            "img": "static/images/list"
        },
        {
            "id": 10,
            "name": "【12.12提前购】【新品上市】A407UB-顽石14寸轻薄窄边框笔记本（Windows10home/i5-7200U/4G内存/500GB+128G SSD)-冰柱金",
            "price": 7599,
            "img": "static/images/list"
        }, {
            "id": 11,
            "name": "【12.12提前购】【新品上市】A407UB-顽石14寸轻薄窄边框笔记本（Windows10home/i5-7200U/4G内存/500GB+128G SSD)-冰柱金",
            "price": 4599,
            "img": "static/images/list"
        },
        {
            "id": 12,
            "name": "【12.12提前购】灵耀S 2代 S4300UN-14英寸炫彩窄边框轻薄本（Windows10home/i5-8250U/8GB/512GB SSD/MX150显卡)-冰钻金",
            "price": 5499,
            "img": "static/images/list"
        },
        {
            "id": 13,
            "name": "【12.12提前购】【新品上市】A407UB-顽石14寸轻薄窄边框笔记本（Windows10home/i5-7200U/4G内存/500GB+128G SSD)-冰柱金",
            "price": 8599,
            "img": "static/images/list"
        },
        {
            "id": 14,
            "name": "【12.12提前购】【新品上市】A407UB-顽石14寸轻薄窄边框笔记本（Windows10home/i5-7200U/4G内存/500GB+128G SSD)-冰柱金",
            "price": 6599,
            "img": "static/images/list"
        },
        {
            "id": 15,
            "name": "【12.12提前购】【新品上市】A407UB-顽石14寸轻薄窄边框笔记本（Windows10home/i5-7200U/4G内存/500GB+128G SSD)-冰柱金",
            "price": 7599,
            "img": "static/images/list"
        }, {
            "id": 16,
            "name": "【12.12提前购】【新品上市】A407UB-顽石14寸轻薄窄边框笔记本（Windows10home/i5-7200U/4G内存/500GB+128G SSD)-冰柱金",
            "price": 4599,
            "img": "static/images/list"
        },
        {
            "id": 17,
            "name": "【12.12提前购】灵耀S 2代 S4300UN-14英寸炫彩窄边框轻薄本（Windows10home/i5-8250U/8GB/512GB SSD/MX150显卡)-冰钻金",
            "price": 5499,
            "img": "static/images/list"
        },
        {
            "id": 18,
            "name": "【12.12提前购】【新品上市】A407UB-顽石14寸轻薄窄边框笔记本（Windows10home/i5-7200U/4G内存/500GB+128G SSD)-冰柱金",
            "price": 8599,
            "img": "static/images/list"
        },
        {
            "id": 19,
            "name": "【12.12提前购】【新品上市】A407UB-顽石14寸轻薄窄边框笔记本（Windows10home/i5-7200U/4G内存/500GB+128G SSD)-冰柱金",
            "price": 6599,
            "img": "static/images/list"
        },
        {
            "id": 20,
            "name": "【12.12提前购】【新品上市】A407UB-顽石14寸轻薄窄边框笔记本（Windows10home/i5-7200U/4G内存/500GB+128G SSD)-冰柱金",
            "price": 7599,
            "img": "static/images/list"
        }, {
            "id": 21,
            "name": "【12.12提前购】【新品上市】A407UB-顽石14寸轻薄窄边框笔记本（Windows10home/i5-7200U/4G内存/500GB+128G SSD)-冰柱金",
            "price": 4599,
            "img": "static/images/list"
        },
        {
            "id": 22,
            "name": "【12.12提前购】灵耀S 2代 S4300UN-14英寸炫彩窄边框轻薄本（Windows10home/i5-8250U/8GB/512GB SSD/MX150显卡)-冰钻金",
            "price": 5499,
            "img": "static/images/list"
        },
        {
            "id": 23,
            "name": "【12.12提前购】【新品上市】A407UB-顽石14寸轻薄窄边框笔记本（Windows10home/i5-7200U/4G内存/500GB+128G SSD)-冰柱金",
            "price": 8599,
            "img": "static/images/list"
        },
        {
            "id": 24,
            "name": "【12.12提前购】【新品上市】A407UB-顽石14寸轻薄窄边框笔记本（Windows10home/i5-7200U/4G内存/500GB+128G SSD)-冰柱金",
            "price": 6599,
            "img": "static/images/list"
        },
        {
            "id": 25,
            "name": "【12.12提前购】【新品上市】A407UB-顽石14寸轻薄窄边框笔记本（Windows10home/i5-7200U/4G内存/500GB+128G SSD)-冰柱金",
            "price": 7599,
            "img": "static/images/list"
        }
    ]
}